aim/VERSION
aim/__init__.py
aim/__version__.py
aim/acme.py
aim/catboost.py
aim/fastai.py
aim/hugging_face.py
aim/keras.py
aim/keras_tuner.py
aim/lightgbm.py
aim/mxnet.py
aim/optuna.py
aim/paddle.py
aim/prophet.py
aim/pytorch.py
aim/pytorch_ignite.py
aim/pytorch_lightning.py
aim/sb3.py
aim/tensorflow.py
aim/xgboost.py
aim/_core/__init__.py
aim/_core/error_handling.py
aim/_core/callbacks/__init__.py
aim/_core/callbacks/caller.py
aim/_core/callbacks/events.py
aim/_core/callbacks/helpers.py
aim/_core/cleanup/__init__.py
aim/_core/storage/__init__.py
aim/_core/storage/arrayview.cpp
aim/_core/storage/arrayview.cpython-38-darwin.so
aim/_core/storage/arrayview.pxd
aim/_core/storage/arrayview.py
aim/_core/storage/encoding.cpython-38-darwin.so
aim/_core/storage/env.py
aim/_core/storage/hashing.cpython-38-darwin.so
aim/_core/storage/inmemorytreeview.cpp
aim/_core/storage/inmemorytreeview.cpython-38-darwin.so
aim/_core/storage/inmemorytreeview.pxd
aim/_core/storage/inmemorytreeview.py
aim/_core/storage/locking.py
aim/_core/storage/object.py
aim/_core/storage/treearrayview.cpp
aim/_core/storage/treearrayview.cpython-38-darwin.so
aim/_core/storage/treearrayview.pxd
aim/_core/storage/treearrayview.py
aim/_core/storage/treeutils.cpp
aim/_core/storage/treeutils.cpython-38-darwin.so
aim/_core/storage/treeutils.pyx
aim/_core/storage/treeutils_non_native.py
aim/_core/storage/treeview.cpp
aim/_core/storage/treeview.cpython-38-darwin.so
aim/_core/storage/treeview.pxd
aim/_core/storage/treeview.py
aim/_core/storage/types.py
aim/_core/storage/utils.cpp
aim/_core/storage/utils.cpython-38-darwin.so
aim/_core/storage/utils.pxd
aim/_core/storage/utils.py
aim/_core/storage/artifacts/__init__.py
aim/_core/storage/artifacts/artifact_registry.py
aim/_core/storage/artifacts/artifact_storage.py
aim/_core/storage/artifacts/filesystem_storage.py
aim/_core/storage/artifacts/s3_storage.py
aim/_core/storage/embedded/container.pxd
aim/_core/storage/embedded/containertreeview.pxd
aimhub_client-1.1.2.dist-info/METADATA
aimhub_client-1.1.2.dist-info/WHEEL
aimhub_client-1.1.2.dist-info/entry_points.txt
aimhub_client-1.1.2.dist-info/top_level.txt
aimhub_client-1.1.2.dist-info/RECORD
