Metadata-Version: 2.1
Name: aimhub-client
Version: 1.1.2
Summary: A super-easy way to record, search and compare AI experiments.
Classifier: License :: OSI Approved :: Apache Software License
Classifier: Programming Language :: Python
Classifier: Programming Language :: Python :: 3
Classifier: Programming Language :: Python :: 3.7
Classifier: Programming Language :: Python :: 3.8
Classifier: Programming Language :: Python :: 3.9
Classifier: Programming Language :: Python :: 3.10
Classifier: Programming Language :: Python :: 3.11
Classifier: Programming Language :: Python :: Implementation :: PyPy
Requires-Python: >=3.7.0
Requires-Dist: aimrocks ==0.5.1
Requires-Dist: cachetools >=4.0.0
Requires-Dist: click >=7.0
Requires-Dist: cryptography >=3.0
Requires-Dist: filelock <4,>=3.3.0
Requires-Dist: numpy <2,>=1.12.0
Requires-Dist: psutil >=5.6.7
Requires-Dist: RestrictedPython >=5.1
Requires-Dist: tqdm >=4.20.0
Requires-Dist: Pillow >=8.0.0
Requires-Dist: packaging >=15.0
Requires-Dist: websockets
Requires-Dist: requests
Requires-Dist: importlib-metadata
Requires-Dist: tabulate
Requires-Dist: boto3
